setup.py
strictdict/__init__.py
strictdict.egg-info/PKG-INFO
strictdict.egg-info/SOURCES.txt
strictdict.egg-info/dependency_links.txt
strictdict.egg-info/requires.txt
strictdict.egg-info/top_level.txt
strictdict/api/__init__.py
strictdict/fields/__init__.py
strictdict/simplifiers/__init__.py
strictdict/strictbase/__init__.py
strictdict/strictbase/strictdict.py
strictdict/tests/__init__.py
strictdict/tests/test_fields.py
strictdict/tests/test_strict_dict.py
strictdict/validators/__init__.py