Metadata-Version: 1.0
Name: strictdict
Version: 0.4
Summary: Strict Dict
Home-page: UNKNOWN
Author: Dmitry Zhiltsov
Author-email: dzhiltsov@me.com
License: UNKNOWN
Platform: UNKNOWN
